CHANGES.txt
LICENSE.txt
README.rst
requirements.txt
setup.conf
setup.py
cryptoassetdata/__init__.py
cryptoassetdata/main.py
cryptoassetdata.egg-info/PKG-INFO
cryptoassetdata.egg-info/SOURCES.txt
cryptoassetdata.egg-info/dependency_links.txt
cryptoassetdata.egg-info/requires.txt
cryptoassetdata.egg-info/top_level.txt
cryptoassetdata/lib/__init__.py
cryptoassetdata/lib/cache.py
cryptoassetdata/lib/downloader.py
cryptoassetdata/lib/extractor.py
cryptoassetdata/lib/logging.py