Metadata-Version: 1.2
Name: cryptoassetdata
Version: 0.0.3
Summary: Fetch historic crypto asset data from CoinMarketCap
Home-page: https://github.com/linuskohl/cryptoassetdata
Author: Linus Kohl
Author-email: linus@munichresearch.com
License: GPLv3
Keywords: cryptocurrency,cryptoassets,crypto,token,bitcoin,data,historic,coinmarketcap
Platform: UNKNOWN
Classifier: Programming Language :: Python :: 3
Classifier: License :: OSI Approved :: GNU General Public License v3 (GPLv3)
Classifier: Operating System :: OS Independent
Requires-Python: >=3.0
